devcore/__about__.py
devcore/__init__.py
devcore/__main__.py
devcore_k-0.1.7.dist-info/METADATA
devcore_k-0.1.7.dist-info/WHEEL
devcore_k-0.1.7.dist-info/entry_points.txt
devcore_k-0.1.7.dist-info/top_level.txt
devcore_k-0.1.7.dist-info/RECORD
