Metadata-Version: 2.1
Name: devcore-k
Version: 0.1.7
Summary: Meta package for python development environment
Home-page: https://github.com/paradoxxxzero/devcore
Author: Florian Mounier
Author-email: paradoxxx.zero@gmail.com
License: MIT
Platform: Any
Provides: devcore
Requires-Dist: log-colorizer-hook-k
Requires-Dist: flask-wdb-hook-k
Requires-Dist: wdb-k
Requires-Dist: isort
Requires-Dist: importmagic3
Requires-Dist: cutter
Requires-Dist: better-exceptions
Requires-Dist: semver
Requires-Dist: black (==18.9b0)
